swagger_bundler/__init__.py
swagger_bundler/bundling.py
swagger_bundler/cmd.py
swagger_bundler/composing.py
swagger_bundler/config.py
swagger_bundler/context.py
swagger_bundler/highlight.py
swagger_bundler/langhelpers.py
swagger_bundler/loading.py
swagger_bundler/ordering.py
swagger_bundler/orphancheck.py
swagger_bundler/postscript.py
swagger_bundler/prefixing.py
swagger_bundler/validation.py
swagger_bundler/watch.py
swagger_bundler/schema/swagger-2.0.json
swagger_bundler-0.1.10.6.dist-info/DESCRIPTION.rst
swagger_bundler-0.1.10.6.dist-info/entry_points.txt
swagger_bundler-0.1.10.6.dist-info/METADATA
swagger_bundler-0.1.10.6.dist-info/metadata.json
swagger_bundler-0.1.10.6.dist-info/RECORD
swagger_bundler-0.1.10.6.dist-info/top_level.txt
swagger_bundler-0.1.10.6.dist-info/WHEEL
