Metadata-Version: 2.0
Name: swagger-bundler
Version: 0.1.10.6
Summary: swagger schema bundler
Home-page: https://github.com/podhmo/swagger-bundler
Author: podhmo
Author-email: UNKNOWN
License: UNKNOWN
Platform: UNKNOWN
Classifier: Programming Language :: Python
Classifier: Programming Language :: Python :: Implementation :: CPython
Classifier: Programming Language :: Python :: 3
Requires-Dist: PyYAML
Requires-Dist: click
Requires-Dist: magicalimport
Provides-Extra: docs
Provides-Extra: testing
Provides-Extra: validation
Requires-Dist: jsonschema; extra == 'validation'
Provides-Extra: watch
Requires-Dist: watchdog; extra == 'watch'
